{
    "parameterSets": {
        "3 hooks": {
            "$fn": "40",
            "curve_thickness": "1.5",
            "handle_count": "3",
            "handle_diameter": "6",
            "handle_offset": "5",
            "handle_spacing": "25",
            "handle_tol": "0.5",
            "mount_base_height": "15",
            "mount_base_length": "60",
            "mount_base_thickness": "1",
            "mount_tab_enable": "false",
            "mount_tab_length": "20",
            "mount_tab_thickness": "0.6"
        },
        "1 hooks": {
            "$fn": "40",
            "curve_thickness": "1.5",
            "handle_count": "1",
            "handle_diameter": "6",
            "handle_offset": "5",
            "handle_spacing": "25",
            "handle_tol": "0.5",
            "mount_base_height": "15",
            "mount_base_length": "30",
            "mount_base_thickness": "1",
            "mount_tab_enable": "false",
            "mount_tab_length": "20",
            "mount_tab_thickness": "0.6"
        },
        "2 hook": {
            "$fn": "40",
            "curve_thickness": "1.5",
            "handle_count": "2",
            "handle_diameter": "6",
            "handle_offset": "5",
            "handle_spacing": "25",
            "handle_tol": "0.5",
            "mount_base_height": "15",
            "mount_base_length": "60",
            "mount_base_thickness": "1",
            "mount_tab_enable": "false",
            "mount_tab_length": "20",
            "mount_tab_thickness": "0.6"
        }
    },
    "parameterSets": "",
    "fileFormatVersion": "1",
    "parameterSets": "",
    "parameterSets": ""
}
